CHANGES.txt
CONTRIBUTORS.txt
MANIFEST.in
README.rst
setup.py
blogofile_blog/__init__.py
blogofile_blog/commands.py
blogofile_blog.egg-info/PKG-INFO
blogofile_blog.egg-info/SOURCES.txt
blogofile_blog.egg-info/dependency_links.txt
blogofile_blog.egg-info/entry_points.txt
blogofile_blog.egg-info/not-zip-safe
blogofile_blog.egg-info/pbr.json
blogofile_blog.egg-info/requires.txt
blogofile_blog.egg-info/top_level.txt
blogofile_blog/site_src/404.html
blogofile_blog/site_src/_config.py
blogofile_blog/site_src/_htaccess
blogofile_blog/site_src/crossdomain.xml
blogofile_blog/site_src/favicon.ico
blogofile_blog/site_src/index.html.mako
blogofile_blog/site_src/robots.txt
blogofile_blog/site_src/_controllers/blog/__init__.py
blogofile_blog/site_src/_controllers/blog/archives.py
blogofile_blog/site_src/_controllers/blog/categories.py
blogofile_blog/site_src/_controllers/blog/chronological.py
blogofile_blog/site_src/_controllers/blog/feed.py
blogofile_blog/site_src/_controllers/blog/permapage.py
blogofile_blog/site_src/_controllers/blog/post.py
blogofile_blog/site_src/_filters/markdown_template.py
blogofile_blog/site_src/_filters/rst_template.py
blogofile_blog/site_src/_filters/syntax_highlight.py
blogofile_blog/site_src/_filters/textile_template.py
blogofile_blog/site_src/_posts/000 - filler1.markdown
blogofile_blog/site_src/_posts/000 - filler2.markdown
blogofile_blog/site_src/_posts/000 - filler3.markdown
blogofile_blog/site_src/_posts/000 - filler4.markdown
blogofile_blog/site_src/_posts/001 - post 1.markdown
blogofile_blog/site_src/_posts/002 - post 2.markdown
blogofile_blog/site_src/_posts/003 - unpublished draft.markdown
blogofile_blog/site_src/_posts/007 - unicode test.markdown
blogofile_blog/site_src/_posts/008 - post 8 - syntax highlight.markdown
blogofile_blog/site_src/_templates/base.mako
blogofile_blog/site_src/_templates/body_scripts.mako
blogofile_blog/site_src/_templates/footer.mako
blogofile_blog/site_src/_templates/head.mako
blogofile_blog/site_src/_templates/header.mako
blogofile_blog/site_src/_templates/sidebar.mako
blogofile_blog/site_src/_templates/site.mako
blogofile_blog/site_src/_templates/theme.mako
blogofile_blog/site_src/_templates/blog/archive_index.mako
blogofile_blog/site_src/_templates/blog/atom.mako
